metadspy/__init__.py
metadspy/__main__.py
metadspy/cli.py
metadspy/generator.py
metadspy/parser.py
metadspy/specs/__init__.py
metadspy/specs/llm.py
metadspy/specs/module.py
metadspy/specs/signature.py
metadspy/templates/llm.j2
metadspy/templates/main.j2
metadspy/templates/module.j2
metadspy/templates/signature.j2
metadspy-0.1.0.dist-info/METADATA
metadspy-0.1.0.dist-info/WHEEL
metadspy-0.1.0.dist-info/entry_points.txt
metadspy-0.1.0.dist-info/RECORD
