Metadata-Version: 2.3
Name: metadspy
Version: 0.1.0
Summary: 
Author: Franck Stéphane Ndzomga
Author-email: 101533724+fsndzomga@users.noreply.github.com
Requires-Python: >=3.10,<3.14
Classifier: Programming Language :: Python :: 3
Classifier: Programming Language :: Python :: 3.10
Classifier: Programming Language :: Python :: 3.11
Classifier: Programming Language :: Python :: 3.12
Classifier: Programming Language :: Python :: 3.13
Requires-Dist: dspy (>=2.6.27,<3.0.0)
Requires-Dist: jinja2 (>=3.1.6,<4.0.0)
Requires-Dist: pydantic (>=2.11.6,<3.0.0)
Requires-Dist: python-dotenv (>=1.1.0,<2.0.0)
Requires-Dist: ruamel-yaml (>=0.18.14,<0.19.0)
Requires-Dist: typer (>=0.16.0,<0.17.0)
